LICENSE
MANIFEST.in
README.rst
requirements-dev.orig.txt
requirements-dev.txt
requirements-test.orig.txt
requirements-test.txt
requirements.orig.txt
requirements.txt
setup.cfg
setup.py
ct_core_api/__init__.py
ct_core_api/_main.py
ct_core_api.egg-info/PKG-INFO
ct_core_api.egg-info/SOURCES.txt
ct_core_api.egg-info/dependency_links.txt
ct_core_api.egg-info/not-zip-safe
ct_core_api.egg-info/requires.txt
ct_core_api.egg-info/top_level.txt
ct_core_api/api/.DS_Store
ct_core_api/api/__init__.py
ct_core_api/api/app/__init__.py
ct_core_api/api/app/config.py
ct_core_api/api/app/debugging.py
ct_core_api/api/app/factory.py
ct_core_api/api/app/logging.py
ct_core_api/api/app/middleware.py
ct_core_api/api/app/runner.py
ct_core_api/api/app/templating.py
ct_core_api/api/app/commands/__init__.py
ct_core_api/api/app/commands/app_cmd.py
ct_core_api/api/app/commands/db_cmd.py
ct_core_api/api/app/commands/shell_cmd.py
ct_core_api/api/app/extensions/__init__.py
ct_core_api/api/app/extensions/celery_ext.py
ct_core_api/api/app/extensions/cors_ext.py
ct_core_api/api/app/extensions/debug_api_ext.py
ct_core_api/api/app/extensions/dogpile_cache_ext.py
ct_core_api/api/app/extensions/login_manager_ext.py
ct_core_api/api/app/extensions/marshmallow_ext.py
ct_core_api/api/app/extensions/oauth2_ext.py
ct_core_api/api/app/extensions/principal_ext.py
ct_core_api/api/app/extensions/sqlalchemy_ext.py
ct_core_api/api/app/extensions/uuid_ext.py
ct_core_api/api/app/modules/__init__.py
ct_core_api/api/app/modules/debug_api/__init__.py
ct_core_api/api/app/modules/debug_api/cache_resources.py
ct_core_api/api/app/modules/debug_api/config_resources.py
ct_core_api/api/app/modules/debug_api/error_resources.py
ct_core_api/api/app/modules/debug_api/log_resources.py
ct_core_api/api/app/modules/health/__init__.py
ct_core_api/api/app/modules/health/health_views.py
ct_core_api/api/app/modules/index/__init__.py
ct_core_api/api/app/modules/index/index_views.py
ct_core_api/api/app/modules/swagger_ui/__init__.py
ct_core_api/api/app/modules/swagger_ui/changelog_views.py
ct_core_api/api/app/modules/swagger_ui/deprecation_schedule_views.py
ct_core_api/api/app/modules/swagger_ui/swagger_ui_views.py
